pytest_bigquery_mock/__init__.py
pytest_bigquery_mock/plugin.py
pytest_bigquery_mock-0.1.1.dist-info/LICENSE
pytest_bigquery_mock-0.1.1.dist-info/METADATA
pytest_bigquery_mock-0.1.1.dist-info/WHEEL
pytest_bigquery_mock-0.1.1.dist-info/entry_points.txt
pytest_bigquery_mock-0.1.1.dist-info/top_level.txt
pytest_bigquery_mock-0.1.1.dist-info/RECORD
