Metadata-Version: 2.1
Name: pytest-bigquery-mock
Version: 0.1.1
Summary: Provides a mock fixture for python bigquery client
Home-page: https://github.com/pjlast/pytest-bigquery-mock
Author: Petri-Johan Last
Author-email: petri.last@gmail.com
License: MIT
Download-URL: https://github.com/pjlast/pytest-bigquery-mock/archive/refs/tags/0.1.1.tar.gz
Platform: UNKNOWN
License-File: LICENSE
Requires-Dist: pytest (>=5.0)
Requires-Dist: pytest-mock (>=3.6)
